pyacc/__init__.py
pyacc/__main__.py
pyacc/api.py
pyacc/util.py
pyacc/commands/__init__.py
pyacc/commands/bib.py
pyacc/commands/dump.py
pyacc/commands/ls.py
pyacc-0.1.0.dist-info/LICENSE
pyacc-0.1.0.dist-info/METADATA
pyacc-0.1.0.dist-info/WHEEL
pyacc-0.1.0.dist-info/entry_points.txt
pyacc-0.1.0.dist-info/top_level.txt
pyacc-0.1.0.dist-info/RECORD
